{"cameraMode":{"drawMode":0,"name":"Shaded","section":"Shading Mode"},"sceneLighting":true,"audioPlay":false,"sceneViewState":{"m_AlwaysRefresh":false,"showFog":true,"showSkybox":true,"showFlares":true,"showImageEffects":true,"showParticleSystems":true,"showVisualEffectGraphs":true,"m_FxEnabled":true},"in2DMode":false,"pivot":{"x":617.6326293945313,"y":12.58113956451416,"z":873.186279296875},"rotation":{"x":0.27997612953186037,"y":0.6021193265914917,"z":-0.238668754696846,"w":0.7086532711982727},"size":26.208894729614259,"orthographic":false}